pyudp/__init__.py
pyudp/client.py
pyudp/multicast_client.py
pyudp/multicast_server.py
pyudp/py.typed
pyudp/server.py
pyudp/utils/__init__.py
pyudp/utils/replacing_queue.py
pyudp-0.1.4.dist-info/METADATA
pyudp-0.1.4.dist-info/WHEEL
pyudp-0.1.4.dist-info/RECORD
