Metadata-Version: 2.3
Name: pyudp
Version: 0.1.4
Summary: A simple UDP client and server
Author-email: takumi-nishimura <clp13218@nitech.jp>
Requires-Python: >=3.8
